h5pyvol/__init__.py
h5pyvol-1.0.dev0.dist-info/LICENSE.txt
h5pyvol-1.0.dev0.dist-info/METADATA
h5pyvol-1.0.dev0.dist-info/WHEEL
h5pyvol-1.0.dev0.dist-info/top_level.txt
h5pyvol-1.0.dev0.dist-info/RECORD
