Metadata-Version: 2.1
Name: h5pyvol
Version: 1.0.dev0
Summary: Abstract data model for HDF5 Python virtual object layers
Home-page: https://github.com/pierlauro/H5PyVOL
Author: pierlauro
License: GNU Affero General Public License v3.0
Project-URL: Bug Tracker, https://github.com/pierlauro/H5PyVOL/issues
Project-URL: Source, https://github.com/pierlauro/H5PyVOL
Keywords: hdf5 vol h5py
Platform: UNKNOWN
Classifier: Development Status :: 5 - Production/Stable
Classifier: Intended Audience :: Developers
Classifier: Programming Language :: Python :: 3.5
Classifier: Programming Language :: Python :: 3.6
Classifier: Programming Language :: Python :: 3.7
Requires-Python: >=3.5
